umami/__init__.py
umami/urls.py
umami/errors/__init__.py
umami/impl/__init__.py
umami/models/__init__.py
umami_analytics-0.3.21.dist-info/METADATA
umami_analytics-0.3.21.dist-info/WHEEL
umami_analytics-0.3.21.dist-info/licenses/LICENSE
umami_analytics-0.3.21.dist-info/RECORD
