Metadata-Version: 2.4
Name: umami-analytics
Version: 0.3.21
Summary: Umami Analytics Client for Python
Project-URL: Homepage, https://github.com/mikeckennedy/umami-python
Project-URL: Tracker, https://github.com/mikeckennedy/umami-python/issues
Project-URL: Source, https://github.com/mikeckennedy/umami-python
Author-email: Michael Kennedy <michael@talkpython.fm>
License-Expression: MIT
License-File: LICENSE
Keywords: analytics,umami,website
Classifier: Development Status :: 4 - Beta
Classifier: License :: OSI Approved :: MIT License
Classifier: Programming Language :: Python
Classifier: Programming Language :: Python :: 3
Classifier: Programming Language :: Python :: 3.10
Classifier: Programming Language :: Python :: 3.11
Classifier: Programming Language :: Python :: 3.12
Classifier: Programming Language :: Python :: 3.13
Classifier: Programming Language :: Python :: 3.14
Requires-Python: >=3.10
Requires-Dist: httpx
Requires-Dist: pydantic
